sf_devtools/__init__.py
sf_devtools/main.py
sf_devtools/commands/__init__.py
sf_devtools/commands/dev.py
sf_devtools/commands/org.py
sf_devtools/commands/package.py
sf_devtools/core/__init__.py
sf_devtools/core/common.py
sf_devtools/core/salesforce.py
sf_devtools/miscs/help.py
sf_devtools/modules/__init__.py
sf_devtools/modules/config.py
sf_devtools/modules/core_package.py
sf_devtools/modules/manifest_manager.py
sf_devtools/modules/mes_package.py
sf_devtools/modules/package_deploy.py
sf_devtools/modules/package_service.py
sf_devtools/modules/scratch_org.py
sf_devtools/modules/sfdmu_sync.py
sf_devtools/modules/main_project/__init__.py
sf_devtools/modules/main_project/convert_deploy_ops.py
sf_devtools/modules/main_project/git_ops.py
sf_devtools/modules/main_project/manifest_ops.py
sf_devtools/modules/main_project/org_config.py
sf_devtools/modules/main_project/retrieve_ops.py
sf_devtools/tests/conftest.py
sf_devtools/tests/test_convert_deploy_ops.py
sf_devtools/tests/test_git_ops.py
sf_devtools/tests/test_manifest_ops.py
sf_devtools/tests/test_org_config.py
sf_devtools/tests/test_retrieve_ops.py
sf_devtools/ui/__init__.py
sf_devtools/ui/git_menu.py
sf_devtools/ui/help_views.py
sf_devtools/ui/interactive.py
sf_devtools/ui/mes_menu.py
sf_devtools/ui/sanwa_main.py
sanwa_sf_devtools-0.2.0.dist-info/METADATA
sanwa_sf_devtools-0.2.0.dist-info/WHEEL
sanwa_sf_devtools-0.2.0.dist-info/entry_points.txt
sanwa_sf_devtools-0.2.0.dist-info/licenses/LICENSE
sanwa_sf_devtools-0.2.0.dist-info/RECORD
